ydb_backend/__init__.py
ydb_backend/backend/__init__.py
ydb_backend/backend/base.py
ydb_backend/backend/client.py
ydb_backend/backend/creation.py
ydb_backend/backend/features.py
ydb_backend/backend/introspection.py
ydb_backend/backend/operations.py
ydb_backend/backend/schema.py
ydb_backend/backend/validation.py
ydb_backend/models/__init__.py
ydb_backend/models/manager.py
ydb_backend/models/sql/__init__.py
ydb_backend/models/sql/compiler.py
ydb_backend/version.py
django_ydb_backend-0.0.1b1.dist-info/METADATA
django_ydb_backend-0.0.1b1.dist-info/WHEEL
django_ydb_backend-0.0.1b1.dist-info/RECORD
