Metadata-Version: 2.3
Name: django-ydb-backend
Version: 0.0.1b1
Summary: Django backend for YDB
Author: Yandex LLC
Author-email: ydb@yandex-team.ru
Requires-Python: >=3.8,<4
Classifier: Programming Language :: Python :: 3
Classifier: Programming Language :: Python :: 3.8
Classifier: Programming Language :: Python :: 3.9
Classifier: Programming Language :: Python :: 3.10
Classifier: Programming Language :: Python :: 3.11
Classifier: Programming Language :: Python :: 3.12
Classifier: Programming Language :: Python :: 3.13
Requires-Dist: django (>=3.2.0,<6.0.0)
Requires-Dist: ydb-dbapi (>=0.1.8,<0.2.0)
